<?xml version="1.0" encoding="UTF-8" standalone="yes"?>
<ns3:dov-schema xmlns:ns3="http://kern.schemas.dov.vlaanderen.be">
    <grondwaterlocatie>
        <identificatie>431/73/4</identificatie>
        <dataidentifier>
            <permkey>2017-001177</permkey>
            <uri>https://oefen.dov.vlaanderen.be/data/put/2017-001177</uri>
        </dataidentifier>
        <grondwaterlocatieType>PUT</grondwaterlocatieType>
        <boring>B/431/73/4</boring>
        <puntligging>
            <xy>
                <x>113733.72</x>
                <y>170591.45</y>
                <betrouwbaarheid>goed</betrouwbaarheid>
                <methode_opmeten>methode onbekend</methode_opmeten>
                <origine_opmeten>
                    <naam>VMM - Afdeling Operationeel Waterbeheer</naam>
                </origine_opmeten>
            </xy>
            <oorspronkelijk_maaiveld>
                <waarde>87.95</waarde>
                <betrouwbaarheid>goed</betrouwbaarheid>
                <methode_opmeten>methode onbekend</methode_opmeten>
                <origine_opmeten>
                    <naam>VMM - Afdeling Operationeel Waterbeheer</naam>
                </origine_opmeten>
            </oorspronkelijk_maaiveld>
            <start_tov_maaiveld>
                <gestart_op>MAAIVELD</gestart_op>
            </start_tov_maaiveld>
        </puntligging>
        <diepte>8.4</diepte>
        <datum_ingebruikname>2003-06-20</datum_ingebruikname>
        <putsoort>verbuisde boorput</putsoort>
        <beheer>
            <vanaf>2003-06-20</vanaf>
            <beheerder>
                <naam>VMM - AFDELING WATER</naam>
            </beheerder>
        </beheer>
        <opmerking>
            <tekst>Bulk Toevoeging GPS Coördinaten ( x:113733,724 Y:170591,454 ) opgemeten op
                22/04/2015 door:ATO (Meest recent maaiveld:87,952 mTAW)
                XYZ waarden vóór de automatische bulk update:
                {"xy":{"x":113733.72,"y":170591.45,"betrouwbaarheid":"goed","methodeOpmeten":"methode
                onbekend","origineOpmeten":{"naam":"VMM - Afdeling Operationeel
                Waterbeheer"}},"oorspronkelijkMaaiveld":{"waarde":87.95,"betrouwbaarheid":"goed","methodeOpmeten":"methode
                onbekend","origineOpmeten":{"naam":"VMM - Afdeling Operationeel Waterbeheer"}}}.</tekst>
            <auteur>
                <naam>Tinneke De Rouck</naam>
            </auteur>
            <datum>2023-04-19</datum>
        </opmerking>
    </grondwaterlocatie>
    <grondwaterlocatie>
        <identificatie>1-1083</identificatie>
        <dataidentifier>
            <permkey>2017-002483</permkey>
            <uri>https://oefen.dov.vlaanderen.be/data/put/2017-002483</uri>
        </dataidentifier>
        <grondwaterlocatieType>PUT</grondwaterlocatieType>
        <puntligging>
            <xy>
                <x>161343.62</x>
                <y>241167.18</y>
                <betrouwbaarheid>goed</betrouwbaarheid>
                <methode_opmeten>methode onbekend</methode_opmeten>
                <origine_opmeten>
                    <naam>VMM - Afdeling Operationeel Waterbeheer</naam>
                </origine_opmeten>
            </xy>
            <oorspronkelijk_maaiveld>
                <waarde>17.35</waarde>
                <betrouwbaarheid>goed</betrouwbaarheid>
                <methode_opmeten>methode onbekend</methode_opmeten>
                <origine_opmeten>
                    <naam>VMM - Afdeling Operationeel Waterbeheer</naam>
                </origine_opmeten>
            </oorspronkelijk_maaiveld>
            <start_tov_maaiveld>
                <gestart_op>MAAIVELD</gestart_op>
            </start_tov_maaiveld>
        </puntligging>
        <diepte>186.28</diepte>
        <datum_ingebruikname>1975-04-01</datum_ingebruikname>
        <putsoort>verbuisde boorput</putsoort>
        <beheer>
            <vanaf>2004-04-05</vanaf>
            <beheerder>
                <naam>VMM - AFDELING WATER</naam>
            </beheerder>
        </beheer>
        <opmerking>
            <tekst>Bulk Toevoeging GPS Coördinaten ( X: 161343.62 Y:241167.18) opgemeten op
                13/01/2010 door Guido Lieben (Meest recent maaiveld: 17.35 mTAW)
                XYZ waarden vóór de automatische bulk update:
                {"xy":{"x":161343.62,"y":241167.18,"betrouwbaarheid":"goed","methodeOpmeten":"methode
                onbekend","origineOpmeten":{"naam":"VMM - Afdeling Operationeel
                Waterbeheer"}},"oorspronkelijkMaaiveld":{"waarde":17.35,"betrouwbaarheid":"goed","methodeOpmeten":"methode
                onbekend","origineOpmeten":{"naam":"VMM - Afdeling Operationeel Waterbeheer"}}}.</tekst>
            <auteur>
                <naam>Tinneke De Rouck</naam>
            </auteur>
            <datum>2023-04-19</datum>
        </opmerking>
    </grondwaterlocatie>
    <grondwaterlocatie>
        <identificatie>1-0542</identificatie>
        <dataidentifier>
            <permkey>2017-000135</permkey>
            <uri>https://oefen.dov.vlaanderen.be/data/put/2017-000135</uri>
        </dataidentifier>
        <grondwaterlocatieType>PUT</grondwaterlocatieType>
        <boring>B/1-0542</boring>
        <puntligging>
            <xy>
                <x>191109.62</x>
                <y>233550.72</y>
                <betrouwbaarheid>goed</betrouwbaarheid>
                <methode_opmeten>methode onbekend</methode_opmeten>
                <origine_opmeten>
                    <naam>VMM - Afdeling Operationeel Waterbeheer</naam>
                </origine_opmeten>
            </xy>
            <oorspronkelijk_maaiveld>
                <waarde>31.71</waarde>
                <betrouwbaarheid>onbekend</betrouwbaarheid>
                <methode_opmeten>methode onbekend</methode_opmeten>
                <origine_opmeten>
                    <naam>VMM - Afdeling Operationeel Waterbeheer</naam>
                </origine_opmeten>
            </oorspronkelijk_maaiveld>
            <start_tov_maaiveld>
                <gestart_op>MAAIVELD</gestart_op>
            </start_tov_maaiveld>
        </puntligging>
        <diepte>5</diepte>
        <datum_ingebruikname>1986-07-03</datum_ingebruikname>
        <putsoort>verbuisde boorput</putsoort>
        <beheer>
            <vanaf>1994-04-10</vanaf>
            <beheerder>
                <naam>VMM - AFDELING WATER</naam>
            </beheerder>
        </beheer>
        <opmerking>
            <tekst>Bulk Toevoeging GPS Coördinaten ( X: 191109.62 Y:233550.72) opgemeten op
                21/10/2009 door Guido Lieben (Meest recent maaiveld: 31.71 mTAW)
                XYZ waarden vóór de automatische bulk update:
                {"xy":{"x":191109.62,"y":233550.72,"betrouwbaarheid":"goed","methodeOpmeten":"methode
                onbekend","origineOpmeten":{"naam":"VMM - Afdeling Operationeel
                Waterbeheer"}},"oorspronkelijkMaaiveld":{"waarde":31.71,"betrouwbaarheid":"onbekend","methodeOpmeten":"methode
                onbekend","origineOpmeten":{"naam":"VMM - Afdeling Operationeel Waterbeheer"}}}.</tekst>
            <auteur>
                <naam>Tinneke De Rouck</naam>
            </auteur>
            <datum>2023-04-19</datum>
        </opmerking>
    </grondwaterlocatie>
    <grondwaterlocatie>
        <identificatie>1-0560</identificatie>
        <dataidentifier>
            <permkey>2017-000140</permkey>
            <uri>https://oefen.dov.vlaanderen.be/data/put/2017-000140</uri>
        </dataidentifier>
        <grondwaterlocatieType>PUT</grondwaterlocatieType>
        <boring>B/1-0560</boring>
        <puntligging>
            <xy>
                <x>181496.16</x>
                <y>232046.28</y>
                <betrouwbaarheid>goed</betrouwbaarheid>
                <methode_opmeten>methode onbekend</methode_opmeten>
                <origine_opmeten>
                    <naam>VMM - Afdeling Operationeel Waterbeheer</naam>
                </origine_opmeten>
            </xy>
            <oorspronkelijk_maaiveld>
                <waarde>22.5</waarde>
                <betrouwbaarheid>onbekend</betrouwbaarheid>
                <methode_opmeten>methode onbekend</methode_opmeten>
                <origine_opmeten>
                    <naam>VMM - Afdeling Operationeel Waterbeheer</naam>
                </origine_opmeten>
            </oorspronkelijk_maaiveld>
            <start_tov_maaiveld>
                <gestart_op>MAAIVELD</gestart_op>
            </start_tov_maaiveld>
        </puntligging>
        <diepte>14</diepte>
        <datum_ingebruikname>1986-08-25</datum_ingebruikname>
        <putsoort>verbuisde boorput</putsoort>
        <beheer>
            <vanaf>1994-11-24</vanaf>
            <beheerder>
                <naam>VMM - AFDELING WATER</naam>
            </beheerder>
        </beheer>
        <opmerking>
            <tekst>Bulk Toevoeging GPS Coördinaten ( X: 181496.16 Y:232046.28) opgemeten op
                11/04/2009 door Guido Lieben (Meest recent maaiveld: 22.5 mTAW)
                XYZ waarden vóór de automatische bulk update:
                {"xy":{"x":181496.16,"y":232046.28,"betrouwbaarheid":"goed","methodeOpmeten":"methode
                onbekend","origineOpmeten":{"naam":"VMM - Afdeling Operationeel
                Waterbeheer"}},"oorspronkelijkMaaiveld":{"waarde":22.5,"betrouwbaarheid":"onbekend","methodeOpmeten":"methode
                onbekend","origineOpmeten":{"naam":"VMM - Afdeling Operationeel Waterbeheer"}}}.</tekst>
            <auteur>
                <naam>Tinneke De Rouck</naam>
            </auteur>
            <datum>2023-04-19</datum>
        </opmerking>
    </grondwaterlocatie>
    <grondwaterlocatie>
        <identificatie>1-0511</identificatie>
        <dataidentifier>
            <permkey>2017-000126</permkey>
            <uri>https://oefen.dov.vlaanderen.be/data/put/2017-000126</uri>
        </dataidentifier>
        <grondwaterlocatieType>PUT</grondwaterlocatieType>
        <boring>B/1-0511</boring>
        <puntligging>
            <xy>
                <x>159381.23</x>
                <y>194546.09</y>
                <betrouwbaarheid>goed</betrouwbaarheid>
                <methode_opmeten>methode onbekend</methode_opmeten>
                <origine_opmeten>
                    <naam>VMM - Afdeling Operationeel Waterbeheer</naam>
                </origine_opmeten>
            </xy>
            <oorspronkelijk_maaiveld>
                <waarde>6.94</waarde>
                <betrouwbaarheid>goed</betrouwbaarheid>
                <methode_opmeten>methode onbekend</methode_opmeten>
                <origine_opmeten>
                    <naam>VMM - Afdeling Operationeel Waterbeheer</naam>
                </origine_opmeten>
            </oorspronkelijk_maaiveld>
            <start_tov_maaiveld>
                <gestart_op>MAAIVELD</gestart_op>
            </start_tov_maaiveld>
        </puntligging>
        <diepte>78</diepte>
        <datum_ingebruikname>1989-06-01</datum_ingebruikname>
        <putsoort>verbuisde boorput</putsoort>
        <beheer>
            <vanaf>1990-03-14</vanaf>
            <beheerder>
                <naam>VMM - AFDELING WATER</naam>
            </beheerder>
        </beheer>
        <opmerking>
            <tekst>Bulk Toevoeging GPS Coördinaten ( X: 159381.23 Y:194546.09) opgemeten op
                28/01/2010 door Guido Lieben (Meest recent maaiveld: 6.94 mTAW)
                XYZ waarden vóór de automatische bulk update:
                {"xy":{"x":159381.23,"y":194546.09,"betrouwbaarheid":"goed","methodeOpmeten":"methode
                onbekend","origineOpmeten":{"naam":"VMM - Afdeling Operationeel
                Waterbeheer"}},"oorspronkelijkMaaiveld":{"waarde":6.94,"betrouwbaarheid":"goed","methodeOpmeten":"methode
                onbekend","origineOpmeten":{"naam":"VMM - Afdeling Operationeel Waterbeheer"}}}.</tekst>
            <auteur>
                <naam>Tinneke De Rouck</naam>
            </auteur>
            <datum>2023-04-19</datum>
        </opmerking>
    </grondwaterlocatie>
    <grondwaterlocatie>
        <identificatie>1-0287</identificatie>
        <dataidentifier>
            <permkey>2017-002462</permkey>
            <uri>https://oefen.dov.vlaanderen.be/data/put/2017-002462</uri>
        </dataidentifier>
        <grondwaterlocatieType>PUT</grondwaterlocatieType>
        <boring>B/1-0287</boring>
        <puntligging>
            <xy>
                <x>195391.14</x>
                <y>235862.3</y>
                <betrouwbaarheid>goed</betrouwbaarheid>
                <methode_opmeten>methode onbekend</methode_opmeten>
                <origine_opmeten>
                    <naam>VMM - Afdeling Operationeel Waterbeheer</naam>
                </origine_opmeten>
            </xy>
            <oorspronkelijk_maaiveld>
                <waarde>28.68</waarde>
                <betrouwbaarheid>goed</betrouwbaarheid>
                <methode_opmeten>methode onbekend</methode_opmeten>
                <origine_opmeten>
                    <naam>VMM - Afdeling Operationeel Waterbeheer</naam>
                </origine_opmeten>
            </oorspronkelijk_maaiveld>
            <start_tov_maaiveld>
                <gestart_op>MAAIVELD</gestart_op>
            </start_tov_maaiveld>
        </puntligging>
        <diepte>143.9</diepte>
        <datum_ingebruikname>1978-01-01</datum_ingebruikname>
        <putsoort>verbuisde boorput</putsoort>
        <beheer>
            <vanaf>2004-02-25</vanaf>
            <beheerder>
                <naam>VMM - AFDELING WATER</naam>
            </beheerder>
        </beheer>
        <opmerking>
            <tekst>Bulk Toevoeging GPS Coördinaten ( X: 195391.14 Y:235862.3) opgemeten op
                21/10/2009 door Guido Lieben (Meest recent maaiveld: 28.68 mTAW)
                XYZ waarden vóór de automatische bulk update:
                {"xy":{"x":195391.14,"y":235862.3,"betrouwbaarheid":"goed","methodeOpmeten":"methode
                onbekend","origineOpmeten":{"naam":"VMM - Afdeling Operationeel
                Waterbeheer"}},"oorspronkelijkMaaiveld":{"waarde":28.68,"betrouwbaarheid":"goed","methodeOpmeten":"methode
                onbekend","origineOpmeten":{"naam":"VMM - Afdeling Operationeel Waterbeheer"}}}.</tekst>
            <auteur>
                <naam>Tinneke De Rouck</naam>
            </auteur>
            <datum>2023-04-19</datum>
        </opmerking>
    </grondwaterlocatie>
    <grondwaterlocatie>
        <identificatie>1-0510</identificatie>
        <dataidentifier>
            <permkey>2017-000125</permkey>
            <uri>https://oefen.dov.vlaanderen.be/data/put/2017-000125</uri>
        </dataidentifier>
        <grondwaterlocatieType>PUT</grondwaterlocatieType>
        <boring>B/1-0510</boring>
        <puntligging>
            <xy>
                <x>159383.51</x>
                <y>194546.82</y>
                <betrouwbaarheid>goed</betrouwbaarheid>
                <methode_opmeten>methode onbekend</methode_opmeten>
                <origine_opmeten>
                    <naam>VMM - Afdeling Operationeel Waterbeheer</naam>
                </origine_opmeten>
            </xy>
            <oorspronkelijk_maaiveld>
                <waarde>7.02</waarde>
                <betrouwbaarheid>goed</betrouwbaarheid>
                <methode_opmeten>methode onbekend</methode_opmeten>
                <origine_opmeten>
                    <naam>VMM - Afdeling Operationeel Waterbeheer</naam>
                </origine_opmeten>
            </oorspronkelijk_maaiveld>
            <start_tov_maaiveld>
                <gestart_op>MAAIVELD</gestart_op>
            </start_tov_maaiveld>
        </puntligging>
        <diepte>24</diepte>
        <datum_ingebruikname>1989-06-01</datum_ingebruikname>
        <putsoort>verbuisde boorput</putsoort>
        <beheer>
            <vanaf>1990-02-14</vanaf>
            <beheerder>
                <naam>VMM - AFDELING WATER</naam>
            </beheerder>
        </beheer>
        <opmerking>
            <tekst>Bulk Toevoeging GPS Coördinaten ( X: 159383.51 Y:194546.82) opgemeten op
                28/01/2010 door Guido Lieben (Meest recent maaiveld: 7.02 mTAW)
                XYZ waarden vóór de automatische bulk update:
                {"xy":{"x":159383.51,"y":194546.82,"betrouwbaarheid":"goed","methodeOpmeten":"methode
                onbekend","origineOpmeten":{"naam":"VMM - Afdeling Operationeel
                Waterbeheer"}},"oorspronkelijkMaaiveld":{"waarde":7.02,"betrouwbaarheid":"goed","methodeOpmeten":"methode
                onbekend","origineOpmeten":{"naam":"VMM - Afdeling Operationeel Waterbeheer"}}}.</tekst>
            <auteur>
                <naam>Tinneke De Rouck</naam>
            </auteur>
            <datum>2023-04-19</datum>
        </opmerking>
    </grondwaterlocatie>
    <grondwaterlocatie>
        <identificatie>1-1089</identificatie>
        <dataidentifier>
            <permkey>2017-002487</permkey>
            <uri>https://oefen.dov.vlaanderen.be/data/put/2017-002487</uri>
        </dataidentifier>
        <grondwaterlocatieType>PUT</grondwaterlocatieType>
        <puntligging>
            <xy>
                <x>179150.7</x>
                <y>212315.15</y>
                <betrouwbaarheid>goed</betrouwbaarheid>
                <methode_opmeten>methode onbekend</methode_opmeten>
                <origine_opmeten>
                    <naam>VMM - Afdeling Operationeel Waterbeheer</naam>
                </origine_opmeten>
            </xy>
            <oorspronkelijk_maaiveld>
                <waarde>13</waarde>
                <betrouwbaarheid>goed</betrouwbaarheid>
                <methode_opmeten>methode onbekend</methode_opmeten>
                <origine_opmeten>
                    <naam>VMM - Afdeling Operationeel Waterbeheer</naam>
                </origine_opmeten>
            </oorspronkelijk_maaiveld>
            <start_tov_maaiveld>
                <gestart_op>MAAIVELD</gestart_op>
            </start_tov_maaiveld>
        </puntligging>
        <diepte>27.92</diepte>
        <datum_ingebruikname>1978-01-01</datum_ingebruikname>
        <putsoort>verbuisde boorput</putsoort>
        <beheer>
            <vanaf>2004-04-05</vanaf>
            <beheerder>
                <naam>VMM - AFDELING WATER</naam>
            </beheerder>
        </beheer>
        <opmerking>
            <tekst>Bulk Toevoeging GPS Coördinaten ( X: 179150.7 Y:212315.15) opgemeten op
                27/01/2010 door Guido Lieben (Meest recent maaiveld: 13 mTAW)
                XYZ waarden vóór de automatische bulk update:
                {"xy":{"x":179150.7,"y":212315.15,"betrouwbaarheid":"goed","methodeOpmeten":"methode
                onbekend","origineOpmeten":{"naam":"VMM - Afdeling Operationeel
                Waterbeheer"}},"oorspronkelijkMaaiveld":{"waarde":13,"betrouwbaarheid":"goed","methodeOpmeten":"methode
                onbekend","origineOpmeten":{"naam":"VMM - Afdeling Operationeel Waterbeheer"}}}.</tekst>
            <auteur>
                <naam>Tinneke De Rouck</naam>
            </auteur>
            <datum>2023-04-19</datum>
        </opmerking>
    </grondwaterlocatie>
    <grondwaterlocatie>
        <identificatie>1-1082</identificatie>
        <dataidentifier>
            <permkey>2017-002482</permkey>
            <uri>https://oefen.dov.vlaanderen.be/data/put/2017-002482</uri>
        </dataidentifier>
        <grondwaterlocatieType>PUT</grondwaterlocatieType>
        <puntligging>
            <xy>
                <x>161335.88</x>
                <y>241169.34</y>
                <betrouwbaarheid>goed</betrouwbaarheid>
                <methode_opmeten>methode onbekend</methode_opmeten>
                <origine_opmeten>
                    <naam>VMM - Afdeling Operationeel Waterbeheer</naam>
                </origine_opmeten>
            </xy>
            <oorspronkelijk_maaiveld>
                <waarde>17.31</waarde>
                <betrouwbaarheid>goed</betrouwbaarheid>
                <methode_opmeten>methode onbekend</methode_opmeten>
                <origine_opmeten>
                    <naam>VMM - Afdeling Operationeel Waterbeheer</naam>
                </origine_opmeten>
            </oorspronkelijk_maaiveld>
            <start_tov_maaiveld>
                <gestart_op>MAAIVELD</gestart_op>
            </start_tov_maaiveld>
        </puntligging>
        <diepte>85.78</diepte>
        <datum_ingebruikname>1975-04-01</datum_ingebruikname>
        <putsoort>verbuisde boorput</putsoort>
        <beheer>
            <vanaf>2004-04-05</vanaf>
            <beheerder>
                <naam>VMM - AFDELING WATER</naam>
            </beheerder>
        </beheer>
        <opmerking>
            <tekst>Bulk Toevoeging GPS Coördinaten ( X: 161335.88 Y:241169.34) opgemeten op
                13/01/2010 door Guido Lieben (Meest recent maaiveld: 17.31 mTAW)
                XYZ waarden vóór de automatische bulk update:
                {"xy":{"x":161335.88,"y":241169.34,"betrouwbaarheid":"goed","methodeOpmeten":"methode
                onbekend","origineOpmeten":{"naam":"VMM - Afdeling Operationeel
                Waterbeheer"}},"oorspronkelijkMaaiveld":{"waarde":17.31,"betrouwbaarheid":"goed","methodeOpmeten":"methode
                onbekend","origineOpmeten":{"naam":"VMM - Afdeling Operationeel Waterbeheer"}}}.</tekst>
            <auteur>
                <naam>Tinneke De Rouck</naam>
            </auteur>
            <datum>2023-04-19</datum>
        </opmerking>
    </grondwaterlocatie>
    <grondwaterlocatie>
        <identificatie>1-0508</identificatie>
        <dataidentifier>
            <permkey>2017-000123</permkey>
            <uri>https://oefen.dov.vlaanderen.be/data/put/2017-000123</uri>
        </dataidentifier>
        <grondwaterlocatieType>PUT</grondwaterlocatieType>
        <boring>B/1-0508</boring>
        <puntligging>
            <xy>
                <x>162761.17</x>
                <y>191039.64</y>
                <betrouwbaarheid>goed</betrouwbaarheid>
                <methode_opmeten>methode onbekend</methode_opmeten>
                <origine_opmeten>
                    <naam>VMM - Afdeling Operationeel Waterbeheer</naam>
                </origine_opmeten>
            </xy>
            <oorspronkelijk_maaiveld>
                <waarde>7.55</waarde>
                <betrouwbaarheid>goed</betrouwbaarheid>
                <methode_opmeten>methode onbekend</methode_opmeten>
                <origine_opmeten>
                    <naam>VMM - Afdeling Operationeel Waterbeheer</naam>
                </origine_opmeten>
            </oorspronkelijk_maaiveld>
            <start_tov_maaiveld>
                <gestart_op>MAAIVELD</gestart_op>
            </start_tov_maaiveld>
        </puntligging>
        <diepte>73</diepte>
        <datum_ingebruikname>1993-03-05</datum_ingebruikname>
        <putsoort>verbuisde boorput</putsoort>
        <beheer>
            <vanaf>1993-04-14</vanaf>
            <beheerder>
                <naam>VMM - AFDELING WATER</naam>
            </beheerder>
        </beheer>
        <opmerking>
            <tekst>Bulk Toevoeging GPS Coördinaten ( X: 162761.17 Y:191039.64) opgemeten op
                03/03/2010 door Guido Lieben (Meest recent maaiveld: 7.55 mTAW)
                XYZ waarden vóór de automatische bulk update:
                {"xy":{"x":162761.17,"y":191039.64,"betrouwbaarheid":"goed","methodeOpmeten":"methode
                onbekend","origineOpmeten":{"naam":"VMM - Afdeling Operationeel
                Waterbeheer"}},"oorspronkelijkMaaiveld":{"waarde":7.55,"betrouwbaarheid":"goed","methodeOpmeten":"methode
                onbekend","origineOpmeten":{"naam":"VMM - Afdeling Operationeel Waterbeheer"}}}.</tekst>
            <auteur>
                <naam>Tinneke De Rouck</naam>
            </auteur>
            <datum>2023-04-19</datum>
        </opmerking>
    </grondwaterlocatie>
    <grondwaterlocatie>
        <identificatie>1-0292</identificatie>
        <dataidentifier>
            <permkey>2017-002463</permkey>
            <uri>https://oefen.dov.vlaanderen.be/data/put/2017-002463</uri>
        </dataidentifier>
        <grondwaterlocatieType>PUT</grondwaterlocatieType>
        <boring>B/1-0292</boring>
        <puntligging>
            <xy>
                <x>179149.34</x>
                <y>212314.14</y>
                <betrouwbaarheid>goed</betrouwbaarheid>
                <methode_opmeten>methode onbekend</methode_opmeten>
                <origine_opmeten>
                    <naam>VMM - Afdeling Operationeel Waterbeheer</naam>
                </origine_opmeten>
            </xy>
            <oorspronkelijk_maaiveld>
                <waarde>13.29</waarde>
                <betrouwbaarheid>goed</betrouwbaarheid>
                <methode_opmeten>methode onbekend</methode_opmeten>
                <origine_opmeten>
                    <naam>VMM - Afdeling Operationeel Waterbeheer</naam>
                </origine_opmeten>
            </oorspronkelijk_maaiveld>
            <start_tov_maaiveld>
                <gestart_op>MAAIVELD</gestart_op>
            </start_tov_maaiveld>
        </puntligging>
        <diepte>11.95</diepte>
        <datum_ingebruikname>1978-01-01</datum_ingebruikname>
        <putsoort>verbuisde boorput</putsoort>
        <beheer>
            <vanaf>2004-04-05</vanaf>
            <beheerder>
                <naam>VMM - AFDELING WATER</naam>
            </beheerder>
        </beheer>
        <opmerking>
            <tekst>Bulk Toevoeging GPS Coördinaten ( X: 179149.34 Y:212314.14) opgemeten op
                27/10/2008 door Guido Lieben (Meest recent maaiveld: 13.29 mTAW)
                XYZ waarden vóór de automatische bulk update:
                {"xy":{"x":179149.34,"y":212314.14,"betrouwbaarheid":"goed","methodeOpmeten":"methode
                onbekend","origineOpmeten":{"naam":"VMM - Afdeling Operationeel
                Waterbeheer"}},"oorspronkelijkMaaiveld":{"waarde":13.29,"betrouwbaarheid":"goed","methodeOpmeten":"methode
                onbekend","origineOpmeten":{"naam":"VMM - Afdeling Operationeel Waterbeheer"}}}.</tekst>
            <auteur>
                <naam>Tinneke De Rouck</naam>
            </auteur>
            <datum>2023-04-19</datum>
        </opmerking>
    </grondwaterlocatie>
    <grondwaterlocatie>
        <identificatie>4-0109</identificatie>
        <dataidentifier>
            <permkey>2017-003688</permkey>
            <uri>https://oefen.dov.vlaanderen.be/data/put/2017-003688</uri>
        </dataidentifier>
        <grondwaterlocatieType>PUT</grondwaterlocatieType>
        <boring>subcropBM-070W0770</boring>
        <puntligging>
            <xy>
                <x>100442.16</x>
                <y>182136.49</y>
                <betrouwbaarheid>goed</betrouwbaarheid>
                <methode_opmeten>methode onbekend</methode_opmeten>
                <origine_opmeten>
                    <naam>VMM - Afdeling Operationeel Waterbeheer</naam>
                </origine_opmeten>
            </xy>
            <oorspronkelijk_maaiveld>
                <waarde>11.15</waarde>
                <betrouwbaarheid>goed</betrouwbaarheid>
                <methode_opmeten>methode onbekend</methode_opmeten>
                <origine_opmeten>
                    <naam>VMM - Afdeling Operationeel Waterbeheer</naam>
                </origine_opmeten>
            </oorspronkelijk_maaiveld>
            <start_tov_maaiveld>
                <gestart_op>MAAIVELD</gestart_op>
            </start_tov_maaiveld>
        </puntligging>
        <diepte>140.5</diepte>
        <datum_ingebruikname>1999-01-01</datum_ingebruikname>
        <putsoort>verbuisde boorput</putsoort>
        <beheer>
            <vanaf>1999-01-01</vanaf>
            <beheerder>
                <naam>VMM - AFDELING WATER</naam>
            </beheerder>
        </beheer>
        <opmerking>
            <tekst>Bulk Toevoeging GPS Coördinaten ( x:100442,16 Y:182136,49 ) opgemeten op
                4/03/2015 door:ATO (Meest recent maaiveld:11,15 mTAW)
                XYZ waarden vóór de automatische bulk update:
                {"xy":{"x":100442.16,"y":182136.49,"betrouwbaarheid":"goed","methodeOpmeten":"methode
                onbekend","origineOpmeten":{"naam":"VMM - Afdeling Operationeel
                Waterbeheer"}},"oorspronkelijkMaaiveld":{"waarde":11.15,"betrouwbaarheid":"goed","methodeOpmeten":"methode
                onbekend","origineOpmeten":{"naam":"VMM - Afdeling Operationeel Waterbeheer"}}}.</tekst>
            <auteur>
                <naam>Tinneke De Rouck</naam>
            </auteur>
            <datum>2023-04-19</datum>
        </opmerking>
    </grondwaterlocatie>
    <grondwaterlocatie>
        <identificatie>2-0085</identificatie>
        <dataidentifier>
            <permkey>2017-000085</permkey>
            <uri>https://oefen.dov.vlaanderen.be/data/put/2017-000085</uri>
        </dataidentifier>
        <grondwaterlocatieType>PUT</grondwaterlocatieType>
        <puntligging>
            <xy>
                <x>180002.87</x>
                <y>184658.95</y>
                <betrouwbaarheid>goed</betrouwbaarheid>
                <methode_opmeten>methode onbekend</methode_opmeten>
                <origine_opmeten>
                    <naam>VMM - Afdeling Operationeel Waterbeheer</naam>
                </origine_opmeten>
            </xy>
            <oorspronkelijk_maaiveld>
                <waarde>14.99</waarde>
                <betrouwbaarheid>goed</betrouwbaarheid>
                <methode_opmeten>methode onbekend</methode_opmeten>
                <origine_opmeten>
                    <naam>VMM - Afdeling Operationeel Waterbeheer</naam>
                </origine_opmeten>
            </oorspronkelijk_maaiveld>
            <start_tov_maaiveld>
                <gestart_op>MAAIVELD</gestart_op>
            </start_tov_maaiveld>
        </puntligging>
        <diepte>63.3</diepte>
        <datum_ingebruikname>1991-01-01</datum_ingebruikname>
        <putsoort>verbuisde boorput</putsoort>
        <beheer>
            <vanaf>1992-09-06</vanaf>
            <beheerder>
                <naam>VMM - AFDELING WATER</naam>
            </beheerder>
        </beheer>
        <opmerking>
            <tekst>Bulk Toevoeging GPS Coördinaten ( X: 180002.87 Y:184658.95) opgemeten op
                03/11/2010 door Guido Lieben (Meest recent maaiveld: 14.99 mTAW)
                XYZ waarden vóór de automatische bulk update:
                {"xy":{"x":180002.87,"y":184658.95,"betrouwbaarheid":"goed","methodeOpmeten":"methode
                onbekend","origineOpmeten":{"naam":"VMM - Afdeling Operationeel
                Waterbeheer"}},"oorspronkelijkMaaiveld":{"waarde":14.99,"betrouwbaarheid":"goed","methodeOpmeten":"methode
                onbekend","origineOpmeten":{"naam":"VMM - Afdeling Operationeel Waterbeheer"}}}.</tekst>
            <auteur>
                <naam>Tinneke De Rouck</naam>
            </auteur>
            <datum>2023-04-19</datum>
        </opmerking>
    </grondwaterlocatie>
    <grondwaterlocatie>
        <identificatie>2-0085</identificatie>
        <dataidentifier>
            <permkey>2017-000085</permkey>
            <uri>https://oefen.dov.vlaanderen.be/data/put/2017-000085</uri>
        </dataidentifier>
        <grondwaterlocatieType>PUT</grondwaterlocatieType>
        <puntligging>
            <xy>
                <x>180002.87</x>
                <y>184658.95</y>
                <betrouwbaarheid>goed</betrouwbaarheid>
                <methode_opmeten>methode onbekend</methode_opmeten>
                <origine_opmeten>
                    <naam>VMM - Afdeling Operationeel Waterbeheer</naam>
                </origine_opmeten>
            </xy>
            <oorspronkelijk_maaiveld>
                <waarde>14.99</waarde>
                <betrouwbaarheid>goed</betrouwbaarheid>
                <methode_opmeten>methode onbekend</methode_opmeten>
                <origine_opmeten>
                    <naam>VMM - Afdeling Operationeel Waterbeheer</naam>
                </origine_opmeten>
            </oorspronkelijk_maaiveld>
            <start_tov_maaiveld>
                <gestart_op>MAAIVELD</gestart_op>
            </start_tov_maaiveld>
        </puntligging>
        <diepte>63.3</diepte>
        <datum_ingebruikname>1991-01-01</datum_ingebruikname>
        <putsoort>verbuisde boorput</putsoort>
        <beheer>
            <vanaf>1992-09-06</vanaf>
            <beheerder>
                <naam>VMM - AFDELING WATER</naam>
            </beheerder>
        </beheer>
        <opmerking>
            <tekst>Bulk Toevoeging GPS Coördinaten ( X: 180002.87 Y:184658.95) opgemeten op
                03/11/2010 door Guido Lieben (Meest recent maaiveld: 14.99 mTAW)
                XYZ waarden vóór de automatische bulk update:
                {"xy":{"x":180002.87,"y":184658.95,"betrouwbaarheid":"goed","methodeOpmeten":"methode
                onbekend","origineOpmeten":{"naam":"VMM - Afdeling Operationeel
                Waterbeheer"}},"oorspronkelijkMaaiveld":{"waarde":14.99,"betrouwbaarheid":"goed","methodeOpmeten":"methode
                onbekend","origineOpmeten":{"naam":"VMM - Afdeling Operationeel Waterbeheer"}}}.</tekst>
            <auteur>
                <naam>Tinneke De Rouck</naam>
            </auteur>
            <datum>2023-04-19</datum>
        </opmerking>
    </grondwaterlocatie>
    <grondwaterlocatie>
        <identificatie>2-0085</identificatie>
        <dataidentifier>
            <permkey>2017-000085</permkey>
            <uri>https://oefen.dov.vlaanderen.be/data/put/2017-000085</uri>
        </dataidentifier>
        <grondwaterlocatieType>PUT</grondwaterlocatieType>
        <puntligging>
            <xy>
                <x>180002.87</x>
                <y>184658.95</y>
                <betrouwbaarheid>goed</betrouwbaarheid>
                <methode_opmeten>methode onbekend</methode_opmeten>
                <origine_opmeten>
                    <naam>VMM - Afdeling Operationeel Waterbeheer</naam>
                </origine_opmeten>
            </xy>
            <oorspronkelijk_maaiveld>
                <waarde>14.99</waarde>
                <betrouwbaarheid>goed</betrouwbaarheid>
                <methode_opmeten>methode onbekend</methode_opmeten>
                <origine_opmeten>
                    <naam>VMM - Afdeling Operationeel Waterbeheer</naam>
                </origine_opmeten>
            </oorspronkelijk_maaiveld>
            <start_tov_maaiveld>
                <gestart_op>MAAIVELD</gestart_op>
            </start_tov_maaiveld>
        </puntligging>
        <diepte>63.3</diepte>
        <datum_ingebruikname>1991-01-01</datum_ingebruikname>
        <putsoort>verbuisde boorput</putsoort>
        <beheer>
            <vanaf>1992-09-06</vanaf>
            <beheerder>
                <naam>VMM - AFDELING WATER</naam>
            </beheerder>
        </beheer>
        <opmerking>
            <tekst>Bulk Toevoeging GPS Coördinaten ( X: 180002.87 Y:184658.95) opgemeten op
                03/11/2010 door Guido Lieben (Meest recent maaiveld: 14.99 mTAW)
                XYZ waarden vóór de automatische bulk update:
                {"xy":{"x":180002.87,"y":184658.95,"betrouwbaarheid":"goed","methodeOpmeten":"methode
                onbekend","origineOpmeten":{"naam":"VMM - Afdeling Operationeel
                Waterbeheer"}},"oorspronkelijkMaaiveld":{"waarde":14.99,"betrouwbaarheid":"goed","methodeOpmeten":"methode
                onbekend","origineOpmeten":{"naam":"VMM - Afdeling Operationeel Waterbeheer"}}}.</tekst>
            <auteur>
                <naam>Tinneke De Rouck</naam>
            </auteur>
            <datum>2023-04-19</datum>
        </opmerking>
    </grondwaterlocatie>
    <grondwaterlocatie>
        <identificatie>4-0242</identificatie>
        <dataidentifier>
            <permkey>2017-002529</permkey>
            <uri>https://oefen.dov.vlaanderen.be/data/put/2017-002529</uri>
        </dataidentifier>
        <grondwaterlocatieType>PUT</grondwaterlocatieType>
        <puntligging>
            <xy>
                <x>111147.52</x>
                <y>209332.99</y>
                <betrouwbaarheid>goed</betrouwbaarheid>
                <methode_opmeten>methode onbekend</methode_opmeten>
                <origine_opmeten>
                    <naam>VMM - Afdeling Operationeel Waterbeheer</naam>
                </origine_opmeten>
            </xy>
            <oorspronkelijk_maaiveld>
                <waarde>7.12</waarde>
                <betrouwbaarheid>goed</betrouwbaarheid>
                <methode_opmeten>methode onbekend</methode_opmeten>
                <origine_opmeten>
                    <naam>VMM - Afdeling Operationeel Waterbeheer</naam>
                </origine_opmeten>
            </oorspronkelijk_maaiveld>
            <start_tov_maaiveld>
                <gestart_op>MAAIVELD</gestart_op>
            </start_tov_maaiveld>
        </puntligging>
        <diepte>5</diepte>
        <datum_ingebruikname>1900-01-01</datum_ingebruikname>
        <putsoort>verbuisde boorput</putsoort>
        <beheer>
            <vanaf>1900-01-01</vanaf>
            <beheerder>
                <naam>VMM - AFDELING WATER</naam>
            </beheerder>
        </beheer>
        <opmerking>
            <tekst>Bulk Toevoeging GPS Coördinaten ( x:111147,52 Y:209332,99 ) opgemeten op
                6/05/2015 door:ATO (Meest recent maaiveld:7,12 mTAW)
                XYZ waarden vóór de automatische bulk update:
                {"xy":{"x":111147.52,"y":209332.99,"betrouwbaarheid":"goed","methodeOpmeten":"methode
                onbekend","origineOpmeten":{"naam":"VMM - Afdeling Operationeel
                Waterbeheer"}},"oorspronkelijkMaaiveld":{"waarde":7.12,"betrouwbaarheid":"goed","methodeOpmeten":"methode
                onbekend","origineOpmeten":{"naam":"VMM - Afdeling Operationeel Waterbeheer"}}}.</tekst>
            <auteur>
                <naam>Tinneke De Rouck</naam>
            </auteur>
            <datum>2023-04-19</datum>
        </opmerking>
    </grondwaterlocatie>
    <grondwaterlocatie>
        <identificatie>2-0125</identificatie>
        <dataidentifier>
            <permkey>2017-000100</permkey>
            <uri>https://oefen.dov.vlaanderen.be/data/put/2017-000100</uri>
        </dataidentifier>
        <grondwaterlocatieType>PUT</grondwaterlocatieType>
        <boring>B/2-0125</boring>
        <puntligging>
            <xy>
                <x>194593.01</x>
                <y>167995.62</y>
                <betrouwbaarheid>goed</betrouwbaarheid>
                <methode_opmeten>methode onbekend</methode_opmeten>
                <origine_opmeten>
                    <naam>VMM - Afdeling Operationeel Waterbeheer</naam>
                </origine_opmeten>
            </xy>
            <oorspronkelijk_maaiveld>
                <waarde>35.47</waarde>
                <betrouwbaarheid>goed</betrouwbaarheid>
                <methode_opmeten>methode onbekend</methode_opmeten>
                <origine_opmeten>
                    <naam>VMM - Afdeling Operationeel Waterbeheer</naam>
                </origine_opmeten>
            </oorspronkelijk_maaiveld>
            <start_tov_maaiveld>
                <gestart_op>MAAIVELD</gestart_op>
            </start_tov_maaiveld>
        </puntligging>
        <diepte>85.5</diepte>
        <datum_ingebruikname>1980-01-01</datum_ingebruikname>
        <datum_uitgebruikname>2012-04-24</datum_uitgebruikname>
        <putsoort>verbuisde boorput</putsoort>
        <beheer>
            <vanaf>1980-09-29</vanaf>
            <beheerder>
                <naam>VMM - AFDELING WATER</naam>
            </beheerder>
        </beheer>
        <opmerking>
            <tekst>Bulk Toevoeging GPS Coördinaten ( X: 194593.01 Y:167995.62) opgemeten op
                12/09/2009 door Guido Lieben (Meest recent maaiveld: 35.47 mTAW)
                XYZ waarden vóór de automatische bulk update:
                {"xy":{"x":194593.01,"y":167995.62,"betrouwbaarheid":"goed","methodeOpmeten":"methode
                onbekend","origineOpmeten":{"naam":"VMM - Afdeling Operationeel
                Waterbeheer"}},"oorspronkelijkMaaiveld":{"waarde":35.47,"betrouwbaarheid":"goed","methodeOpmeten":"methode
                onbekend","origineOpmeten":{"naam":"VMM - Afdeling Operationeel Waterbeheer"}}}.</tekst>
            <auteur>
                <naam>Tinneke De Rouck</naam>
            </auteur>
            <datum>2023-04-19</datum>
        </opmerking>
    </grondwaterlocatie>
    <grondwaterlocatie>
        <identificatie>7-0110</identificatie>
        <dataidentifier>
            <permkey>2017-000234</permkey>
            <uri>https://oefen.dov.vlaanderen.be/data/put/2017-000234</uri>
        </dataidentifier>
        <grondwaterlocatieType>PUT</grondwaterlocatieType>
        <boring>B/7-0110</boring>
        <puntligging>
            <xy>
                <x>247408.91</x>
                <y>203645.78</y>
                <betrouwbaarheid>goed</betrouwbaarheid>
                <methode_opmeten>methode onbekend</methode_opmeten>
                <origine_opmeten>
                    <naam>VMM - Afdeling Operationeel Waterbeheer</naam>
                </origine_opmeten>
            </xy>
            <oorspronkelijk_maaiveld>
                <waarde>33.07</waarde>
                <betrouwbaarheid>goed</betrouwbaarheid>
                <methode_opmeten>methode onbekend</methode_opmeten>
                <origine_opmeten>
                    <naam>VMM - Afdeling Operationeel Waterbeheer</naam>
                </origine_opmeten>
            </oorspronkelijk_maaiveld>
            <start_tov_maaiveld>
                <gestart_op>MAAIVELD</gestart_op>
            </start_tov_maaiveld>
        </puntligging>
        <diepte>21</diepte>
        <datum_ingebruikname>1979-06-19</datum_ingebruikname>
        <putsoort>verbuisde boorput</putsoort>
        <beheer>
            <vanaf>1979-09-26</vanaf>
            <beheerder>
                <naam>VMM - AFDELING WATER</naam>
            </beheerder>
        </beheer>
        <opmerking>
            <tekst>Bulk Toevoeging GPS Coördinaten ( X: 247408.91 Y:203645.78) opgemeten op
                06/03/2009 door Guido Lieben (Meest recent maaiveld: 33.07 mTAW)
                XYZ waarden vóór de automatische bulk update:
                {"xy":{"x":247408.91,"y":203645.78,"betrouwbaarheid":"goed","methodeOpmeten":"methode
                onbekend","origineOpmeten":{"naam":"VMM - Afdeling Operationeel
                Waterbeheer"}},"oorspronkelijkMaaiveld":{"waarde":33.07,"betrouwbaarheid":"goed","methodeOpmeten":"methode
                onbekend","origineOpmeten":{"naam":"VMM - Afdeling Operationeel Waterbeheer"}}}.</tekst>
            <auteur>
                <naam>Tinneke De Rouck</naam>
            </auteur>
            <datum>2023-04-19</datum>
        </opmerking>
    </grondwaterlocatie>
    <grondwaterlocatie>
        <identificatie>1-0347</identificatie>
        <dataidentifier>
            <permkey>2017-002470</permkey>
            <uri>https://oefen.dov.vlaanderen.be/data/put/2017-002470</uri>
        </dataidentifier>
        <grondwaterlocatieType>PUT</grondwaterlocatieType>
        <boring>B/1-0347</boring>
        <puntligging>
            <xy>
                <x>168387.53</x>
                <y>233814.91</y>
                <betrouwbaarheid>goed</betrouwbaarheid>
                <methode_opmeten>methode onbekend</methode_opmeten>
                <origine_opmeten>
                    <naam>VMM - Afdeling Operationeel Waterbeheer</naam>
                </origine_opmeten>
            </xy>
            <oorspronkelijk_maaiveld>
                <waarde>15.48</waarde>
                <betrouwbaarheid>goed</betrouwbaarheid>
                <methode_opmeten>methode onbekend</methode_opmeten>
                <origine_opmeten>
                    <naam>VMM - Afdeling Operationeel Waterbeheer</naam>
                </origine_opmeten>
            </oorspronkelijk_maaiveld>
            <start_tov_maaiveld>
                <gestart_op>MAAIVELD</gestart_op>
            </start_tov_maaiveld>
        </puntligging>
        <diepte>84.33</diepte>
        <datum_ingebruikname>1979-10-01</datum_ingebruikname>
        <putsoort>verbuisde boorput</putsoort>
        <beheer>
            <vanaf>2004-02-26</vanaf>
            <beheerder>
                <naam>VMM - AFDELING WATER</naam>
            </beheerder>
        </beheer>
        <opmerking>
            <tekst>Bulk Toevoeging GPS Coördinaten ( X: 168387.53 Y:233814.91) opgemeten op
                12/02/2009 door Guido Lieben (Meest recent maaiveld: 15.48 mTAW)
                XYZ waarden vóór de automatische bulk update:
                {"xy":{"x":168387.53,"y":233814.91,"betrouwbaarheid":"goed","methodeOpmeten":"methode
                onbekend","origineOpmeten":{"naam":"VMM - Afdeling Operationeel
                Waterbeheer"}},"oorspronkelijkMaaiveld":{"waarde":15.48,"betrouwbaarheid":"goed","methodeOpmeten":"methode
                onbekend","origineOpmeten":{"naam":"VMM - Afdeling Operationeel Waterbeheer"}}}.</tekst>
            <auteur>
                <naam>Tinneke De Rouck</naam>
            </auteur>
            <datum>2023-04-19</datum>
        </opmerking>
    </grondwaterlocatie>
    <grondwaterlocatie>
        <identificatie>1-0396</identificatie>
        <dataidentifier>
            <permkey>2017-002475</permkey>
            <uri>https://oefen.dov.vlaanderen.be/data/put/2017-002475</uri>
        </dataidentifier>
        <grondwaterlocatieType>PUT</grondwaterlocatieType>
        <boring>B/1-0396</boring>
        <puntligging>
            <xy>
                <x>176497.3</x>
                <y>231086.22</y>
                <betrouwbaarheid>goed</betrouwbaarheid>
                <methode_opmeten>methode onbekend</methode_opmeten>
                <origine_opmeten>
                    <naam>VMM - Afdeling Operationeel Waterbeheer</naam>
                </origine_opmeten>
            </xy>
            <oorspronkelijk_maaiveld>
                <waarde>21.18</waarde>
                <betrouwbaarheid>goed</betrouwbaarheid>
                <methode_opmeten>methode onbekend</methode_opmeten>
                <origine_opmeten>
                    <naam>VMM - Afdeling Operationeel Waterbeheer</naam>
                </origine_opmeten>
            </oorspronkelijk_maaiveld>
            <start_tov_maaiveld>
                <gestart_op>MAAIVELD</gestart_op>
            </start_tov_maaiveld>
        </puntligging>
        <diepte>146.78</diepte>
        <datum_ingebruikname>1981-08-12</datum_ingebruikname>
        <putsoort>verbuisde boorput</putsoort>
        <beheer>
            <vanaf>2004-04-05</vanaf>
            <beheerder>
                <naam>VMM - AFDELING WATER</naam>
            </beheerder>
        </beheer>
        <opmerking>
            <tekst>Bulk Toevoeging GPS Coördinaten ( X: 176497.3 Y:231086.22) opgemeten op
                12/02/2009 door Guido Lieben (Meest recent maaiveld: 21.18 mTAW)
                XYZ waarden vóór de automatische bulk update:
                {"xy":{"x":176497.3,"y":231086.22,"betrouwbaarheid":"goed","methodeOpmeten":"methode
                onbekend","origineOpmeten":{"naam":"VMM - Afdeling Operationeel
                Waterbeheer"}},"oorspronkelijkMaaiveld":{"waarde":21.18,"betrouwbaarheid":"goed","methodeOpmeten":"methode
                onbekend","origineOpmeten":{"naam":"VMM - Afdeling Operationeel Waterbeheer"}}}.</tekst>
            <auteur>
                <naam>Tinneke De Rouck</naam>
            </auteur>
            <datum>2023-04-19</datum>
        </opmerking>
    </grondwaterlocatie>
    <grondwaterlocatie>
        <identificatie>1-0396</identificatie>
        <dataidentifier>
            <permkey>2017-002475</permkey>
            <uri>https://oefen.dov.vlaanderen.be/data/put/2017-002475</uri>
        </dataidentifier>
        <grondwaterlocatieType>PUT</grondwaterlocatieType>
        <boring>B/1-0396</boring>
        <puntligging>
            <xy>
                <x>176497.3</x>
                <y>231086.22</y>
                <betrouwbaarheid>goed</betrouwbaarheid>
                <methode_opmeten>methode onbekend</methode_opmeten>
                <origine_opmeten>
                    <naam>VMM - Afdeling Operationeel Waterbeheer</naam>
                </origine_opmeten>
            </xy>
            <oorspronkelijk_maaiveld>
                <waarde>21.18</waarde>
                <betrouwbaarheid>goed</betrouwbaarheid>
                <methode_opmeten>methode onbekend</methode_opmeten>
                <origine_opmeten>
                    <naam>VMM - Afdeling Operationeel Waterbeheer</naam>
                </origine_opmeten>
            </oorspronkelijk_maaiveld>
            <start_tov_maaiveld>
                <gestart_op>MAAIVELD</gestart_op>
            </start_tov_maaiveld>
        </puntligging>
        <diepte>146.78</diepte>
        <datum_ingebruikname>1981-08-12</datum_ingebruikname>
        <putsoort>verbuisde boorput</putsoort>
        <beheer>
            <vanaf>2004-04-05</vanaf>
            <beheerder>
                <naam>VMM - AFDELING WATER</naam>
            </beheerder>
        </beheer>
        <opmerking>
            <tekst>Bulk Toevoeging GPS Coördinaten ( X: 176497.3 Y:231086.22) opgemeten op
                12/02/2009 door Guido Lieben (Meest recent maaiveld: 21.18 mTAW)
                XYZ waarden vóór de automatische bulk update:
                {"xy":{"x":176497.3,"y":231086.22,"betrouwbaarheid":"goed","methodeOpmeten":"methode
                onbekend","origineOpmeten":{"naam":"VMM - Afdeling Operationeel
                Waterbeheer"}},"oorspronkelijkMaaiveld":{"waarde":21.18,"betrouwbaarheid":"goed","methodeOpmeten":"methode
                onbekend","origineOpmeten":{"naam":"VMM - Afdeling Operationeel Waterbeheer"}}}.</tekst>
            <auteur>
                <naam>Tinneke De Rouck</naam>
            </auteur>
            <datum>2023-04-19</datum>
        </opmerking>
    </grondwaterlocatie>
    <grondwaterlocatie>
        <identificatie>1-0278</identificatie>
        <dataidentifier>
            <permkey>2017-000106</permkey>
            <uri>https://oefen.dov.vlaanderen.be/data/put/2017-000106</uri>
        </dataidentifier>
        <grondwaterlocatieType>PUT</grondwaterlocatieType>
        <boring>B/1-0278</boring>
        <puntligging>
            <xy>
                <x>190299.11</x>
                <y>200149.93</y>
                <betrouwbaarheid>goed</betrouwbaarheid>
                <methode_opmeten>methode onbekend</methode_opmeten>
                <origine_opmeten>
                    <naam>VMM - Afdeling Operationeel Waterbeheer</naam>
                </origine_opmeten>
            </xy>
            <oorspronkelijk_maaiveld>
                <waarde>18.49</waarde>
                <betrouwbaarheid>goed</betrouwbaarheid>
                <methode_opmeten>methode onbekend</methode_opmeten>
                <origine_opmeten>
                    <naam>VMM - Afdeling Operationeel Waterbeheer</naam>
                </origine_opmeten>
            </oorspronkelijk_maaiveld>
            <start_tov_maaiveld>
                <gestart_op>MAAIVELD</gestart_op>
            </start_tov_maaiveld>
        </puntligging>
        <diepte>19.5</diepte>
        <datum_ingebruikname>1978-01-01</datum_ingebruikname>
        <putsoort>verbuisde boorput</putsoort>
        <beheer>
            <vanaf>1978-02-14</vanaf>
            <beheerder>
                <naam>VMM - AFDELING WATER</naam>
            </beheerder>
        </beheer>
        <opmerking>
            <tekst>Bulk Toevoeging GPS Coördinaten ( X: 190299.11 Y:200149.93) opgemeten op
                01/06/2010 door Guido Lieben (Meest recent maaiveld: 18.49 mTAW)
                XYZ waarden vóór de automatische bulk update:
                {"xy":{"x":190299.11,"y":200149.93,"betrouwbaarheid":"goed","methodeOpmeten":"methode
                onbekend","origineOpmeten":{"naam":"VMM - Afdeling Operationeel
                Waterbeheer"}},"oorspronkelijkMaaiveld":{"waarde":18.49,"betrouwbaarheid":"goed","methodeOpmeten":"methode
                onbekend","origineOpmeten":{"naam":"VMM - Afdeling Operationeel Waterbeheer"}}}.</tekst>
            <auteur>
                <naam>Tinneke De Rouck</naam>
            </auteur>
            <datum>2023-04-19</datum>
        </opmerking>
    </grondwaterlocatie>
    <grondwaterlocatie>
        <identificatie>1-0455</identificatie>
        <dataidentifier>
            <permkey>2017-000116</permkey>
            <uri>https://oefen.dov.vlaanderen.be/data/put/2017-000116</uri>
        </dataidentifier>
        <grondwaterlocatieType>PUT</grondwaterlocatieType>
        <boring>B/1-0455</boring>
        <puntligging>
            <xy>
                <x>170720.42</x>
                <y>194320.53</y>
                <betrouwbaarheid>goed</betrouwbaarheid>
                <methode_opmeten>methode onbekend</methode_opmeten>
                <origine_opmeten>
                    <naam>VMM - Afdeling Operationeel Waterbeheer</naam>
                </origine_opmeten>
            </xy>
            <oorspronkelijk_maaiveld>
                <waarde>31.58</waarde>
                <betrouwbaarheid>goed</betrouwbaarheid>
                <methode_opmeten>methode onbekend</methode_opmeten>
                <origine_opmeten>
                    <naam>VMM - Afdeling Operationeel Waterbeheer</naam>
                </origine_opmeten>
            </oorspronkelijk_maaiveld>
            <start_tov_maaiveld>
                <gestart_op>MAAIVELD</gestart_op>
            </start_tov_maaiveld>
        </puntligging>
        <diepte>25</diepte>
        <datum_ingebruikname>1987-09-01</datum_ingebruikname>
        <putsoort>verbuisde boorput</putsoort>
        <beheer>
            <vanaf>1989-06-16</vanaf>
            <beheerder>
                <naam>VMM - AFDELING WATER</naam>
            </beheerder>
        </beheer>
        <opmerking>
            <tekst>Bulk Toevoeging GPS Coördinaten ( X: 170720.42 Y:194320.53) opgemeten op
                03/03/2010 door Guido Lieben (Meest recent maaiveld: 31.58 mTAW)
                XYZ waarden vóór de automatische bulk update:
                {"xy":{"x":170720.42,"y":194320.53,"betrouwbaarheid":"goed","methodeOpmeten":"methode
                onbekend","origineOpmeten":{"naam":"VMM - Afdeling Operationeel
                Waterbeheer"}},"oorspronkelijkMaaiveld":{"waarde":31.58,"betrouwbaarheid":"goed","methodeOpmeten":"methode
                onbekend","origineOpmeten":{"naam":"VMM - Afdeling Operationeel Waterbeheer"}}}.</tekst>
            <auteur>
                <naam>Tinneke De Rouck</naam>
            </auteur>
            <datum>2023-04-19</datum>
        </opmerking>
    </grondwaterlocatie>
    <grondwaterlocatie>
        <identificatie>1-1084</identificatie>
        <dataidentifier>
            <permkey>2017-002484</permkey>
            <uri>https://oefen.dov.vlaanderen.be/data/put/2017-002484</uri>
        </dataidentifier>
        <grondwaterlocatieType>PUT</grondwaterlocatieType>
        <puntligging>
            <xy>
                <x>173533.83</x>
                <y>216707.1</y>
                <betrouwbaarheid>goed</betrouwbaarheid>
                <methode_opmeten>methode onbekend</methode_opmeten>
                <origine_opmeten>
                    <naam>VMM - Afdeling Operationeel Waterbeheer</naam>
                </origine_opmeten>
            </xy>
            <oorspronkelijk_maaiveld>
                <waarde>16.83</waarde>
                <betrouwbaarheid>onbekend</betrouwbaarheid>
                <methode_opmeten>methode onbekend</methode_opmeten>
                <origine_opmeten>
                    <naam>VMM - Afdeling Operationeel Waterbeheer</naam>
                </origine_opmeten>
            </oorspronkelijk_maaiveld>
            <start_tov_maaiveld>
                <gestart_op>MAAIVELD</gestart_op>
            </start_tov_maaiveld>
        </puntligging>
        <diepte>46.79</diepte>
        <datum_ingebruikname>1975-01-01</datum_ingebruikname>
        <putsoort>verbuisde boorput</putsoort>
        <beheer>
            <vanaf>2004-03-25</vanaf>
            <beheerder>
                <naam>VMM - AFDELING WATER</naam>
            </beheerder>
        </beheer>
        <opmerking>
            <tekst>Bulk Toevoeging GPS Coördinaten ( X: 173533.83 Y:216707.1) opgemeten op
                02/03/2010 door Guido Lieben (Meest recent maaiveld: 16.83 mTAW)
                XYZ waarden vóór de automatische bulk update:
                {"xy":{"x":173533.83,"y":216707.1,"betrouwbaarheid":"goed","methodeOpmeten":"methode
                onbekend","origineOpmeten":{"naam":"VMM - Afdeling Operationeel
                Waterbeheer"}},"oorspronkelijkMaaiveld":{"waarde":16.83,"betrouwbaarheid":"onbekend","methodeOpmeten":"methode
                onbekend","origineOpmeten":{"naam":"VMM - Afdeling Operationeel Waterbeheer"}}}.</tekst>
            <auteur>
                <naam>Tinneke De Rouck</naam>
            </auteur>
            <datum>2023-04-19</datum>
        </opmerking>
    </grondwaterlocatie>
</ns3:dov-schema>